FlexLogger/Log.py
FlexLogger/Logger.py
FlexLogger/__init__.py
FlexLogger-1.1.6.dist-info/METADATA
FlexLogger-1.1.6.dist-info/WHEEL
FlexLogger-1.1.6.dist-info/top_level.txt
FlexLogger-1.1.6.dist-info/RECORD
