Metadata-Version: 2.1
Name: FlexLogger
Version: 1.1.6
Summary: Wrapper for remote logging to a Database with the help of an API REST.
Author: Anderson
Author-email: anderbytes@gmail.com
Requires-Dist: requests ~=2.32.3
Requires-Dist: fastapi ~=0.115.5
